cctf/__init__.py
cctf/balance.py
cctf/base.py
cctf/core.py
cctf/market.py
cctf/orders.py
cctf/symbol.py
cctf/utils.py
cctf-0.1.2.dist-info/LICENSE
cctf-0.1.2.dist-info/METADATA
cctf-0.1.2.dist-info/WHEEL
cctf-0.1.2.dist-info/top_level.txt
cctf-0.1.2.dist-info/RECORD
