Metadata-Version: 2.1
Name: cctf
Version: 0.1.2
Summary: CCTF
